viro_seq_utils/__init__.py
viro_seq_utils/aln_utils.py
viro_seq_utils/phylo_utils.py
viro_seq_utils/run.py
viro_seq_utils/seq_utils.py
viro_seq_utils/tests/__init__.py
viro_seq_utils/tests/tests_aln_utils.py
viro_seq_utils/tests/tests_seq_utils.py
viro_seq_utils-1.5.0.dist-info/LICENSE
viro_seq_utils-1.5.0.dist-info/METADATA
viro_seq_utils-1.5.0.dist-info/WHEEL
viro_seq_utils-1.5.0.dist-info/top_level.txt
viro_seq_utils-1.5.0.dist-info/RECORD
