Metadata-Version: 2.1
Name: viro-seq-utils
Version: 1.5.0
Summary: Utilities modules for sequences, alignments and phylogeny from Toulouse virology laboratory.
Home-page: https://github.com/BioDReD/python-package-viro-seq-utils
Author: Nicolas Jeanne
Author-email: jeanne.n@chu-toulouse.fr
License: GNU General Public License
Project-URL: Bug Tracker, https://github.com/BioDReD/python-package-viro-seq-utils/issues
Keywords: alignment sequence phylogeny
Classifier: Topic :: Scientific/Engineering :: Bio-Informatics
Classifier: Programming Language :: Python :: 3.6
Classifier: License :: OSI Approved :: GNU General Public License v3 (GPLv3)
Classifier: Intended Audience :: Science/Research
Requires-Python: >=3.6
License-File: LICENSE
Requires-Dist: biopython ==1.84
Requires-Dist: numpy ==1.26.1
